flask_hello_world/__init__.py
flask_hello_world/hello_flask.py
flask_hello_world-1.0.dist-info/METADATA
flask_hello_world-1.0.dist-info/WHEEL
flask_hello_world-1.0.dist-info/top_level.txt
flask_hello_world-1.0.dist-info/RECORD
