Metadata-Version: 2.1
Name: flask-hello-world
Version: 1.0
Summary: Demo Flask hello world
Home-page: https://github.com/davidleeguanwei/flask_hello_world
Author: davidleeguanwei
Author-email: davidleeguanwei@gmail.com
License: MIT
Platform: UNKNOWN
